nlpdatasets/__init__.py
nlpdatasets/__version__.py
nlpdatasets/cli.py
nlpdatasets/paths.py
nlpdatasets/py.typed
nlpdatasets/utils.py
nlpdatasets/datasets/stopwords.txt
nlpdatasets/datasets/userdict.txt
nlpdatasets/datasets/fonts/simhei.ttf
nlpdatasets/datasets/sementic/README.md
nlpdatasets/datasets/sementic/修饰副词.txt
nlpdatasets/datasets/sementic/停用词.txt
nlpdatasets/datasets/sementic/反义关系库.txt
nlpdatasets/datasets/sementic/同义关系库.txt
nlpdatasets/datasets/sementic/否定词.txt
nlpdatasets/datasets/sementic/情态词.txt
nlpdatasets/datasets/sementic/抽象关系库.txt
nlpdatasets/datasets/sementic/数量介词.txt
nlpdatasets/datasets/sementic/程度副词.txt
nlpdatasets/datasets/sementic/简称关系库.txt
nlpdatasets/datasets/sementic/节日时间词.txt
nlpdatasets/datasets/sementic/量比词.txt
nlpdatasets-0.1.5.data/data/LICENSE
nlpdatasets-0.1.5.dist-info/LICENSE
nlpdatasets-0.1.5.dist-info/METADATA
nlpdatasets-0.1.5.dist-info/WHEEL
nlpdatasets-0.1.5.dist-info/entry_points.txt
nlpdatasets-0.1.5.dist-info/top_level.txt
nlpdatasets-0.1.5.dist-info/RECORD
