Metadata-Version: 2.1
Name: nlpdatasets
Version: 0.1.5
Summary: Having fun with language processing 🐳
Home-page: https://github.com/szj2ys/nlpdatasets
Author: szj
Author-email: szj2ys@qq.com
License: MIT
Platform: UNKNOWN
Classifier: License :: OSI Approved :: MIT License
Classifier: Programming Language :: Python :: 3.6
Classifier: Programming Language :: Python :: 3.7
Classifier: Programming Language :: Python :: 3.8
Classifier: Programming Language :: Python :: 3.9
Requires-Python: >=3.6.0
License-File: LICENSE
Requires-Dist: click
Requires-Dist: click-help-colors
Requires-Dist: requests
